k3redisutil/__init__.py
k3redisutil/redis_proxy_cli.py
k3redisutil/redisutil.py
k3redisutil/synopsis.py
k3redisutil-0.1.5.dist-info/licenses/LICENSE
k3redisutil-0.1.5.dist-info/METADATA
k3redisutil-0.1.5.dist-info/WHEEL
k3redisutil-0.1.5.dist-info/top_level.txt
k3redisutil-0.1.5.dist-info/RECORD
